<?xml version="1.0"?>
<opencv_storage>
<opencv_ml_dtree>
  <format>3</format>
  <is_classifier>1</is_classifier>
  <var_all>5</var_all>
  <var_count>4</var_count>
  <ord_var_count>4</ord_var_count>
  <cat_var_count>1</cat_var_count>
  <training_params>
    <use_surrogates>0</use_surrogates>
    <max_categories>10</max_categories>
    <regression_accuracy>9.9999997764825821e-03</regression_accuracy>
    <max_depth>10</max_depth>
    <min_sample_count>1761</min_sample_count>
    <cross_validation_folds>0</cross_validation_folds></training_params>
  <global_var_idx>1</global_var_idx>
  <var_idx>
    0 1 2 3</var_idx>
  <var_type>
    0 0 0 0 1</var_type>
  <cat_ofs>
    0 0 0 0 0 0 0 0</cat_ofs>
  <class_labels>
    0 1</class_labels>
  <missing_subst>
    0. 0. 0. 0. 0.</missing_subst>
  <nodes>
    <_>
      <depth>0</depth>
      <value>0.</value>
      <norm_class_idx>0</norm_class_idx>
      <splits>
        <_><var>1</var>
          <quality>1.6762977500000000e+06</quality>
          <le>1.5950000000000000e+02</le></_></splits></_>
    <_>
      <depth>1</depth>
      <value>0.</value>
      <norm_class_idx>0</norm_class_idx>
      <splits>
        <_><var>1</var>
          <quality>1.6648302500000000e+06</quality>
          <le>1.4550000000000000e+02</le></_></splits></_>
    <_>
      <depth>2</depth>
      <value>0.</value>
      <norm_class_idx>0</norm_class_idx>
      <splits>
        <_><var>1</var>
          <quality>1.5841392500000000e+06</quality>
          <le>1.3750000000000000e+02</le></_></splits></_>
    <_>
      <depth>3</depth>
      <value>0.</value>
      <norm_class_idx>0</norm_class_idx>
      <splits>
        <_><var>1</var>
          <quality>1423351.</quality>
          <le>1.3050000000000000e+02</le></_></splits></_>
    <_>
      <depth>4</depth>
      <value>0.</value>
      <norm_class_idx>0</norm_class_idx>
      <splits>
        <_><var>2</var>
          <quality>1.0577996250000000e+06</quality>
          <le>1.4650000000000000e+02</le></_></splits></_>
    <_>
      <depth>5</depth>
      <value>0.</value>
      <norm_class_idx>0</norm_class_idx>
      <splits>
        <_><var>3</var>
          <quality>1.0341998750000000e+06</quality>
          <le>7.2500000000000000e+01</le></_></splits></_>
    <_>
      <depth>6</depth>
      <value>0.</value>
      <norm_class_idx>0</norm_class_idx>
      <splits>
        <_><var>0</var>
          <quality>4.0213481250000000e+05</quality>
          <le>1.9850000000000000e+02</le></_></splits></_>
    <_>
      <depth>7</depth>
      <value>0.</value>
      <norm_class_idx>0</norm_class_idx>
      <splits>
        <_><var>0</var>
          <quality>3.2455859375000000e+05</quality>
          <le>9.4500000000000000e+01</le></_></splits></_>
    <_>
      <depth>8</depth>
      <value>0.</value>
      <norm_class_idx>0</norm_class_idx>
      <splits>
        <_><var>3</var>
          <quality>5.9461906250000000e+04</quality>
          <le>3.4500000000000000e+01</le></_></splits></_>
    <_>
      <depth>9</depth>
      <value>0.</value>
      <norm_class_idx>0</norm_class_idx>
      <splits>
        <_><var>0</var>
          <quality>2.5906091796875000e+04</quality>
          <le>2.0500000000000000e+01</le></_></splits></_>
    <_>
      <depth>10</depth>
      <value>0.</value>
      <norm_class_idx>0</norm_class_idx></_>
    <_>
      <depth>10</depth>
      <value>0.</value>
      <norm_class_idx>0</norm_class_idx></_>
    <_>
      <depth>9</depth>
      <value>0.</value>
      <norm_class_idx>0</norm_class_idx>
      <splits>
        <_><var>0</var>
          <quality>3.3569210937500000e+04</quality>
          <le>1.9500000000000000e+01</le></_></splits></_>
    <_>
      <depth>10</depth>
      <value>0.</value>
      <norm_class_idx>0</norm_class_idx></_>
    <_>
      <depth>10</depth>
      <value>0.</value>
      <norm_class_idx>0</norm_class_idx></_>
    <_>
      <depth>8</depth>
      <value>0.</value>
      <norm_class_idx>0</norm_class_idx>
      <splits>
        <_><var>1</var>
          <quality>2.6513556250000000e+05</quality>
          <le>1.2250000000000000e+02</le></_></splits></_>
    <_>
      <depth>9</depth>
      <value>0.</value>
      <norm_class_idx>0</norm_class_idx>
      <splits>
        <_><var>0</var>
          <quality>2.2244240234375000e+04</quality>
          <le>1.5950000000000000e+02</le></_></splits></_>
    <_>
      <depth>10</depth>
      <value>0.</value>
      <norm_class_idx>0</norm_class_idx></_>
    <_>
      <depth>10</depth>
      <value>0.</value>
      <norm_class_idx>0</norm_class_idx></_>
    <_>
      <depth>9</depth>
      <value>0.</value>
      <norm_class_idx>0</norm_class_idx>
      <splits>
        <_><var>2</var>
          <quality>2.4293145312500000e+05</quality>
          <le>1.4250000000000000e+02</le></_></splits></_>
    <_>
      <depth>10</depth>
      <value>0.</value>
      <norm_class_idx>0</norm_class_idx></_>
    <_>
      <depth>10</depth>
      <value>0.</value>
      <norm_class_idx>0</norm_class_idx></_>
    <_>
      <depth>7</depth>
      <value>0.</value>
      <norm_class_idx>0</norm_class_idx>
      <splits>
        <_><var>1</var>
          <quality>7.7586226562500000e+04</quality>
          <le>1.2150000000000000e+02</le></_></splits></_>
    <_>
      <depth>8</depth>
      <value>0.</value>
      <norm_class_idx>0</norm_class_idx></_>
    <_>
      <depth>8</depth>
      <value>0.</value>
      <norm_class_idx>0</norm_class_idx>
      <splits>
        <_><var>2</var>
          <quality>7.6751210937500000e+04</quality>
          <le>1.3850000000000000e+02</le></_></splits></_>
    <_>
      <depth>9</depth>
      <value>0.</value>
      <norm_class_idx>0</norm_class_idx>
      <splits>
        <_><var>2</var>
          <quality>7.4433359375000000e+04</quality>
          <le>1.3450000000000000e+02</le></_></splits></_>
    <_>
      <depth>10</depth>
      <value>0.</value>
      <norm_class_idx>0</norm_class_idx></_>
    <_>
      <depth>10</depth>
      <value>0.</value>
      <norm_class_idx>0</norm_class_idx></_>
    <_>
      <depth>9</depth>
      <value>0.</value>
      <norm_class_idx>0</norm_class_idx>
      <splits>
        <_><var>1</var>
          <quality>2.3187692871093750e+03</quality>
          <le>1.2550000000000000e+02</le></_></splits></_>
    <_>
      <depth>10</depth>
      <value>0.</value>
      <norm_class_idx>0</norm_class_idx></_>
    <_>
      <depth>10</depth>
      <value>0.</value>
      <norm_class_idx>0</norm_class_idx></_>
    <_>
      <depth>6</depth>
      <value>0.</value>
      <norm_class_idx>0</norm_class_idx>
      <splits>
        <_><var>3</var>
          <quality>6.3208250000000000e+05</quality>
          <le>1.0150000000000000e+02</le></_></splits></_>
    <_>
      <depth>7</depth>
      <value>0.</value>
      <norm_class_idx>0</norm_class_idx>
      <splits>
        <_><var>1</var>
          <quality>590160.</quality>
          <le>1.1150000000000000e+02</le></_></splits></_>
    <_>
      <depth>8</depth>
      <value>0.</value>
      <norm_class_idx>0</norm_class_idx>
      <splits>
        <_><var>1</var>
          <quality>2.6011701562500000e+05</quality>
          <le>1.0650000000000000e+02</le></_></splits></_>
    <_>
      <depth>9</depth>
      <value>0.</value>
      <norm_class_idx>0</norm_class_idx>
      <splits>
        <_><var>0</var>
          <quality>249272.</quality>
          <le>1.6950000000000000e+02</le></_></splits></_>
    <_>
      <depth>10</depth>
      <value>0.</value>
      <norm_class_idx>0</norm_class_idx></_>
    <_>
      <depth>10</depth>
      <value>0.</value>
      <norm_class_idx>0</norm_class_idx></_>
    <_>
      <depth>9</depth>
      <value>0.</value>
      <norm_class_idx>0</norm_class_idx>
      <splits>
        <_><var>2</var>
          <quality>1.0845042968750000e+04</quality>
          <le>1.0950000000000000e+02</le></_></splits></_>
    <_>
      <depth>10</depth>
      <value>0.</value>
      <norm_class_idx>0</norm_class_idx></_>
    <_>
      <depth>10</depth>
      <value>0.</value>
      <norm_class_idx>0</norm_class_idx></_>
    <_>
      <depth>8</depth>
      <value>0.</value>
      <norm_class_idx>0</norm_class_idx>
      <splits>
        <_><var>0</var>
          <quality>3.3004715625000000e+05</quality>
          <le>2.0750000000000000e+02</le></_></splits></_>
    <_>
      <depth>9</depth>
      <value>0.</value>
      <norm_class_idx>0</norm_class_idx>
      <splits>
        <_><var>3</var>
          <quality>1.9298312500000000e+05</quality>
          <le>8.6500000000000000e+01</le></_></splits></_>
    <_>
      <depth>10</depth>
      <value>0.</value>
      <norm_class_idx>0</norm_class_idx></_>
    <_>
      <depth>10</depth>
      <value>0.</value>
      <norm_class_idx>0</norm_class_idx></_>
    <_>
      <depth>9</depth>
      <value>0.</value>
      <norm_class_idx>0</norm_class_idx>
      <splits>
        <_><var>3</var>
          <quality>1.3706707812500000e+05</quality>
          <le>9.9500000000000000e+01</le></_></splits></_>
    <_>
      <depth>10</depth>
      <value>0.</value>
      <norm_class_idx>0</norm_class_idx></_>
    <_>
      <depth>10</depth>
      <value>0.</value>
      <norm_class_idx>0</norm_class_idx></_>
    <_>
      <depth>7</depth>
      <value>0.</value>
      <norm_class_idx>0</norm_class_idx>
      <splits>
        <_><var>0</var>
          <quality>4.1926757812500000e+04</quality>
          <le>2.1250000000000000e+02</le></_></splits></_>
    <_>
      <depth>8</depth>
      <value>0.</value>
      <norm_class_idx>0</norm_class_idx>
      <splits>
        <_><var>0</var>
          <quality>3.5391429687500000e+04</quality>
          <le>3.7500000000000000e+01</le></_></splits></_>
    <_>
      <depth>9</depth>
      <value>0.</value>
      <norm_class_idx>0</norm_class_idx>
      <splits>
        <_><var>0</var>
          <quality>6.3930927734375000e+03</quality>
          <le>3.2500000000000000e+01</le></_></splits></_>
    <_>
      <depth>10</depth>
      <value>0.</value>
      <norm_class_idx>0</norm_class_idx></_>
    <_>
      <depth>10</depth>
      <value>0.</value>
      <norm_class_idx>0</norm_class_idx></_>
    <_>
      <depth>9</depth>
      <value>0.</value>
      <norm_class_idx>0</norm_class_idx>
      <splits>
        <_><var>2</var>
          <quality>2.8999333984375000e+04</quality>
          <le>1.2850000000000000e+02</le></_></splits></_>
    <_>
      <depth>10</depth>
      <value>0.</value>
      <norm_class_idx>0</norm_class_idx></_>
    <_>
      <depth>10</depth>
      <value>0.</value>
      <norm_class_idx>0</norm_class_idx></_>
    <_>
      <depth>8</depth>
      <value>0.</value>
      <norm_class_idx>0</norm_class_idx>
      <splits>
        <_><var>2</var>
          <quality>6.5370590820312500e+03</quality>
          <le>1.2150000000000000e+02</le></_></splits></_>
    <_>
      <depth>9</depth>
      <value>0.</value>
      <norm_class_idx>0</norm_class_idx></_>
    <_>
      <depth>9</depth>
      <value>0.</value>
      <norm_class_idx>0</norm_class_idx>
      <splits>
        <_><var>0</var>
          <quality>6.1250351562500000e+03</quality>
          <le>2.1950000000000000e+02</le></_></splits></_>
    <_>
      <depth>10</depth>
      <value>0.</value>
      <norm_class_idx>0</norm_class_idx></_>
    <_>
      <depth>10</depth>
      <value>0.</value>
      <norm_class_idx>0</norm_class_idx></_>
    <_>
      <depth>5</depth>
      <value>0.</value>
      <norm_class_idx>0</norm_class_idx>
      <splits>
        <_><var>1</var>
          <quality>2.3701035156250000e+04</quality>
          <le>1.1950000000000000e+02</le></_></splits></_>
    <_>
      <depth>6</depth>
      <value>0.</value>
      <norm_class_idx>0</norm_class_idx>
      <splits>
        <_><var>1</var>
          <quality>1.3406411132812500e+04</quality>
          <le>1.0250000000000000e+02</le></_></splits></_>
    <_>
      <depth>7</depth>
      <value>0.</value>
      <norm_class_idx>0</norm_class_idx></_>
    <_>
      <depth>7</depth>
      <value>0.</value>
      <norm_class_idx>0</norm_class_idx>
      <splits>
        <_><var>0</var>
          <quality>1.9775380859375000e+03</quality>
          <le>1.3250000000000000e+02</le></_></splits></_>
    <_>
      <depth>8</depth>
      <value>0.</value>
      <norm_class_idx>0</norm_class_idx></_>
    <_>
      <depth>8</depth>
      <value>0.</value>
      <norm_class_idx>0</norm_class_idx></_>
    <_>
      <depth>6</depth>
      <value>0.</value>
      <norm_class_idx>0</norm_class_idx>
      <splits>
        <_><var>2</var>
          <quality>1.0451380859375000e+04</quality>
          <le>1.5450000000000000e+02</le></_></splits></_>
    <_>
      <depth>7</depth>
      <value>0.</value>
      <norm_class_idx>0</norm_class_idx>
      <splits>
        <_><var>1</var>
          <quality>9.8615058593750000e+03</quality>
          <le>1.2650000000000000e+02</le></_></splits></_>
    <_>
      <depth>8</depth>
      <value>0.</value>
      <norm_class_idx>0</norm_class_idx>
      <splits>
        <_><var>0</var>
          <quality>1.8923746337890625e+03</quality>
          <le>1.4550000000000000e+02</le></_></splits></_>
    <_>
      <depth>9</depth>
      <value>0.</value>
      <norm_class_idx>0</norm_class_idx></_>
    <_>
      <depth>9</depth>
      <value>0.</value>
      <norm_class_idx>0</norm_class_idx></_>
    <_>
      <depth>8</depth>
      <value>0.</value>
      <norm_class_idx>0</norm_class_idx>
      <splits>
        <_><var>2</var>
          <quality>7.9963061523437500e+03</quality>
          <le>1.5250000000000000e+02</le></_></splits></_>
    <_>
      <depth>9</depth>
      <value>0.</value>
      <norm_class_idx>0</norm_class_idx>
      <splits>
        <_><var>0</var>
          <quality>7.3432353515625000e+03</quality>
          <le>1.7050000000000000e+02</le></_></splits></_>
    <_>
      <depth>10</depth>
      <value>0.</value>
      <norm_class_idx>0</norm_class_idx></_>
    <_>
      <depth>10</depth>
      <value>0.</value>
      <norm_class_idx>0</norm_class_idx></_>
    <_>
      <depth>9</depth>
      <value>0.</value>
      <norm_class_idx>0</norm_class_idx></_>
    <_>
      <depth>7</depth>
      <value>0.</value>
      <norm_class_idx>0</norm_class_idx></_>
    <_>
      <depth>4</depth>
      <value>0.</value>
      <norm_class_idx>0</norm_class_idx>
      <splits>
        <_><var>2</var>
          <quality>3.6565225000000000e+05</quality>
          <le>1.3750000000000000e+02</le></_></splits></_>
    <_>
      <depth>5</depth>
      <value>0.</value>
      <norm_class_idx>0</norm_class_idx>
      <splits>
        <_><var>1</var>
          <quality>1.8012060937500000e+05</quality>
          <le>1.3450000000000000e+02</le></_></splits></_>
    <_>
      <depth>6</depth>
      <value>0.</value>
      <norm_class_idx>0</norm_class_idx>
      <splits>
        <_><var>0</var>
          <quality>1.3299614062500000e+05</quality>
          <le>1.2650000000000000e+02</le></_></splits></_>
    <_>
      <depth>7</depth>
      <value>0.</value>
      <norm_class_idx>0</norm_class_idx>
      <splits>
        <_><var>0</var>
          <quality>3.6723515625000000e+04</quality>
          <le>3.6500000000000000e+01</le></_></splits></_>
    <_>
      <depth>8</depth>
      <value>0.</value>
      <norm_class_idx>0</norm_class_idx>
      <splits>
        <_><var>3</var>
          <quality>2.9763112792968750e+03</quality>
          <le>6.5000000000000000e+00</le></_></splits></_>
    <_>
      <depth>9</depth>
      <value>0.</value>
      <norm_class_idx>0</norm_class_idx></_>
    <_>
      <depth>9</depth>
      <value>0.</value>
      <norm_class_idx>0</norm_class_idx>
      <splits>
        <_><var>2</var>
          <quality>2.4373452148437500e+03</quality>
          <le>1.3450000000000000e+02</le></_></splits></_>
    <_>
      <depth>10</depth>
      <value>0.</value>
      <norm_class_idx>0</norm_class_idx></_>
    <_>
      <depth>10</depth>
      <value>0.</value>
      <norm_class_idx>0</norm_class_idx></_>
    <_>
      <depth>8</depth>
      <value>0.</value>
      <norm_class_idx>0</norm_class_idx>
      <splits>
        <_><var>0</var>
          <quality>3.3750484375000000e+04</quality>
          <le>9.8500000000000000e+01</le></_></splits></_>
    <_>
      <depth>9</depth>
      <value>0.</value>
      <norm_class_idx>0</norm_class_idx>
      <splits>
        <_><var>2</var>
          <quality>1.6818236328125000e+04</quality>
          <le>1.3550000000000000e+02</le></_></splits></_>
    <_>
      <depth>10</depth>
      <value>0.</value>
      <norm_class_idx>0</norm_class_idx></_>
    <_>
      <depth>10</depth>
      <value>0.</value>
      <norm_class_idx>0</norm_class_idx></_>
    <_>
      <depth>9</depth>
      <value>0.</value>
      <norm_class_idx>0</norm_class_idx>
      <splits>
        <_><var>3</var>
          <quality>1.6942494140625000e+04</quality>
          <le>1.0500000000000000e+01</le></_></splits></_>
    <_>
      <depth>10</depth>
      <value>0.</value>
      <norm_class_idx>0</norm_class_idx></_>
    <_>
      <depth>10</depth>
      <value>0.</value>
      <norm_class_idx>0</norm_class_idx></_>
    <_>
      <depth>7</depth>
      <value>0.</value>
      <norm_class_idx>0</norm_class_idx>
      <splits>
        <_><var>2</var>
          <quality>9.6285578125000000e+04</quality>
          <le>1.3250000000000000e+02</le></_></splits></_>
    <_>
      <depth>8</depth>
      <value>0.</value>
      <norm_class_idx>0</norm_class_idx>
      <splits>
        <_><var>0</var>
          <quality>4.3649945312500000e+04</quality>
          <le>1.8650000000000000e+02</le></_></splits></_>
    <_>
      <depth>9</depth>
      <value>0.</value>
      <norm_class_idx>0</norm_class_idx>
      <splits>
        <_><var>2</var>
          <quality>3.4908296875000000e+04</quality>
          <le>1.2550000000000000e+02</le></_></splits></_>
    <_>
      <depth>10</depth>
      <value>0.</value>
      <norm_class_idx>0</norm_class_idx></_>
    <_>
      <depth>10</depth>
      <value>0.</value>
      <norm_class_idx>0</norm_class_idx></_>
    <_>
      <depth>9</depth>
      <value>0.</value>
      <norm_class_idx>0</norm_class_idx>
      <splits>
        <_><var>0</var>
          <quality>8.7471455078125000e+03</quality>
          <le>2.4550000000000000e+02</le></_></splits></_>
    <_>
      <depth>10</depth>
      <value>0.</value>
      <norm_class_idx>0</norm_class_idx></_>
    <_>
      <depth>10</depth>
      <value>0.</value>
      <norm_class_idx>0</norm_class_idx></_>
    <_>
      <depth>8</depth>
      <value>0.</value>
      <norm_class_idx>0</norm_class_idx>
      <splits>
        <_><var>0</var>
          <quality>5.2641890625000000e+04</quality>
          <le>1.4850000000000000e+02</le></_></splits></_>
    <_>
      <depth>9</depth>
      <value>0.</value>
      <norm_class_idx>0</norm_class_idx>
      <splits>
        <_><var>3</var>
          <quality>1.3857702148437500e+04</quality>
          <le>8.5000000000000000e+00</le></_></splits></_>
    <_>
      <depth>10</depth>
      <value>0.</value>
      <norm_class_idx>0</norm_class_idx></_>
    <_>
      <depth>10</depth>
      <value>0.</value>
      <norm_class_idx>0</norm_class_idx></_>
    <_>
      <depth>9</depth>
      <value>0.</value>
      <norm_class_idx>0</norm_class_idx>
      <splits>
        <_><var>3</var>
          <quality>3.8786816406250000e+04</quality>
          <le>9.5000000000000000e+00</le></_></splits></_>
    <_>
      <depth>10</depth>
      <value>0.</value>
      <norm_class_idx>0</norm_class_idx></_>
    <_>
      <depth>10</depth>
      <value>0.</value>
      <norm_class_idx>0</norm_class_idx></_>
    <_>
      <depth>6</depth>
      <value>0.</value>
      <norm_class_idx>0</norm_class_idx>
      <splits>
        <_><var>0</var>
          <quality>4.7155300781250000e+04</quality>
          <le>1.6850000000000000e+02</le></_></splits></_>
    <_>
      <depth>7</depth>
      <value>0.</value>
      <norm_class_idx>0</norm_class_idx>
      <splits>
        <_><var>0</var>
          <quality>3.8028277343750000e+04</quality>
          <le>1.4850000000000000e+02</le></_></splits></_>
    <_>
      <depth>8</depth>
      <value>0.</value>
      <norm_class_idx>0</norm_class_idx>
      <splits>
        <_><var>0</var>
          <quality>3.0057566406250000e+04</quality>
          <le>6.3500000000000000e+01</le></_></splits></_>
    <_>
      <depth>9</depth>
      <value>0.</value>
      <norm_class_idx>0</norm_class_idx>
      <splits>
        <_><var>3</var>
          <quality>3.8729147949218750e+03</quality>
          <le>6.5000000000000000e+00</le></_></splits></_>
    <_>
      <depth>10</depth>
      <value>0.</value>
      <norm_class_idx>0</norm_class_idx></_>
    <_>
      <depth>10</depth>
      <value>0.</value>
      <norm_class_idx>0</norm_class_idx></_>
    <_>
      <depth>9</depth>
      <value>0.</value>
      <norm_class_idx>0</norm_class_idx>
      <splits>
        <_><var>2</var>
          <quality>2.6192201171875000e+04</quality>
          <le>1.3350000000000000e+02</le></_></splits></_>
    <_>
      <depth>10</depth>
      <value>0.</value>
      <norm_class_idx>0</norm_class_idx></_>
    <_>
      <depth>10</depth>
      <value>0.</value>
      <norm_class_idx>0</norm_class_idx></_>
    <_>
      <depth>8</depth>
      <value>0.</value>
      <norm_class_idx>0</norm_class_idx>
      <splits>
        <_><var>3</var>
          <quality>8.0005830078125000e+03</quality>
          <le>3.5000000000000000e+00</le></_></splits></_>
    <_>
      <depth>9</depth>
      <value>0.</value>
      <norm_class_idx>0</norm_class_idx></_>
    <_>
      <depth>9</depth>
      <value>0.</value>
      <norm_class_idx>0</norm_class_idx>
      <splits>
        <_><var>2</var>
          <quality>6.7678115234375000e+03</quality>
          <le>1.2850000000000000e+02</le></_></splits></_>
    <_>
      <depth>10</depth>
      <value>0.</value>
      <norm_class_idx>0</norm_class_idx></_>
    <_>
      <depth>10</depth>
      <value>0.</value>
      <norm_class_idx>0</norm_class_idx></_>
    <_>
      <depth>7</depth>
      <value>0.</value>
      <norm_class_idx>0</norm_class_idx>
      <splits>
        <_><var>0</var>
          <quality>9.1414580078125000e+03</quality>
          <le>2.4450000000000000e+02</le></_></splits></_>
    <_>
      <depth>8</depth>
      <value>0.</value>
      <norm_class_idx>0</norm_class_idx>
      <splits>
        <_><var>2</var>
          <quality>9.1422099609375000e+03</quality>
          <le>1.3450000000000000e+02</le></_></splits></_>
    <_>
      <depth>9</depth>
      <value>0.</value>
      <norm_class_idx>0</norm_class_idx>
      <splits>
        <_><var>0</var>
          <quality>5.7222036132812500e+03</quality>
          <le>1.8150000000000000e+02</le></_></splits></_>
    <_>
      <depth>10</depth>
      <value>0.</value>
      <norm_class_idx>0</norm_class_idx></_>
    <_>
      <depth>10</depth>
      <value>0.</value>
      <norm_class_idx>0</norm_class_idx></_>
    <_>
      <depth>9</depth>
      <value>0.</value>
      <norm_class_idx>0</norm_class_idx>
      <splits>
        <_><var>3</var>
          <quality>3.4224311523437500e+03</quality>
          <le>5.5000000000000000e+00</le></_></splits></_>
    <_>
      <depth>10</depth>
      <value>0.</value>
      <norm_class_idx>0</norm_class_idx></_>
    <_>
      <depth>10</depth>
      <value>0.</value>
      <norm_class_idx>0</norm_class_idx></_>
    <_>
      <depth>8</depth>
      <value>1.</value>
      <norm_class_idx>1</norm_class_idx></_>
    <_>
      <depth>5</depth>
      <value>0.</value>
      <norm_class_idx>0</norm_class_idx>
      <splits>
        <_><var>0</var>
          <quality>1.8559956250000000e+05</quality>
          <le>1.0050000000000000e+02</le></_></splits></_>
    <_>
      <depth>6</depth>
      <value>0.</value>
      <norm_class_idx>0</norm_class_idx>
      <splits>
        <_><var>2</var>
          <quality>2.4292310546875000e+04</quality>
          <le>1.3950000000000000e+02</le></_></splits></_>
    <_>
      <depth>7</depth>
      <value>0.</value>
      <norm_class_idx>0</norm_class_idx>
      <splits>
        <_><var>0</var>
          <quality>7.5308193359375000e+03</quality>
          <le>6.1500000000000000e+01</le></_></splits></_>
    <_>
      <depth>8</depth>
      <value>0.</value>
      <norm_class_idx>0</norm_class_idx></_>
    <_>
      <depth>8</depth>
      <value>0.</value>
      <norm_class_idx>0</norm_class_idx>
      <splits>
        <_><var>0</var>
          <quality>5.8975239257812500e+03</quality>
          <le>8.1500000000000000e+01</le></_></splits></_>
    <_>
      <depth>9</depth>
      <value>0.</value>
      <norm_class_idx>0</norm_class_idx>
      <splits>
        <_><var>3</var>
          <quality>1.9679501953125000e+03</quality>
          <le>1.3500000000000000e+01</le></_></splits></_>
    <_>
      <depth>10</depth>
      <value>0.</value>
      <norm_class_idx>0</norm_class_idx></_>
    <_>
      <depth>10</depth>
      <value>0.</value>
      <norm_class_idx>0</norm_class_idx></_>
    <_>
      <depth>9</depth>
      <value>0.</value>
      <norm_class_idx>0</norm_class_idx>
      <splits>
        <_><var>3</var>
          <quality>3.9377558593750000e+03</quality>
          <le>1.2500000000000000e+01</le></_></splits></_>
    <_>
      <depth>10</depth>
      <value>0.</value>
      <norm_class_idx>0</norm_class_idx></_>
    <_>
      <depth>10</depth>
      <value>0.</value>
      <norm_class_idx>0</norm_class_idx></_>
    <_>
      <depth>7</depth>
      <value>0.</value>
      <norm_class_idx>0</norm_class_idx>
      <splits>
        <_><var>0</var>
          <quality>1.6767054687500000e+04</quality>
          <le>5.1500000000000000e+01</le></_></splits></_>
    <_>
      <depth>8</depth>
      <value>0.</value>
      <norm_class_idx>0</norm_class_idx></_>
    <_>
      <depth>8</depth>
      <value>0.</value>
      <norm_class_idx>0</norm_class_idx>
      <splits>
        <_><var>3</var>
          <quality>1.5528314453125000e+04</quality>
          <le>9.5000000000000000e+00</le></_></splits></_>
    <_>
      <depth>9</depth>
      <value>0.</value>
      <norm_class_idx>0</norm_class_idx></_>
    <_>
      <depth>9</depth>
      <value>0.</value>
      <norm_class_idx>0</norm_class_idx>
      <splits>
        <_><var>0</var>
          <quality>1.5496083007812500e+04</quality>
          <le>8.6500000000000000e+01</le></_></splits></_>
    <_>
      <depth>10</depth>
      <value>0.</value>
      <norm_class_idx>0</norm_class_idx></_>
    <_>
      <depth>10</depth>
      <value>0.</value>
      <norm_class_idx>0</norm_class_idx></_>
    <_>
      <depth>6</depth>
      <value>0.</value>
      <norm_class_idx>0</norm_class_idx>
      <splits>
        <_><var>2</var>
          <quality>1.6134923437500000e+05</quality>
          <le>1.5550000000000000e+02</le></_></splits></_>
    <_>
      <depth>7</depth>
      <value>0.</value>
      <norm_class_idx>0</norm_class_idx>
      <splits>
        <_><var>3</var>
          <quality>1.6046798437500000e+05</quality>
          <le>1.7500000000000000e+01</le></_></splits></_>
    <_>
      <depth>8</depth>
      <value>0.</value>
      <norm_class_idx>0</norm_class_idx>
      <splits>
        <_><var>0</var>
          <quality>1.5476206250000000e+05</quality>
          <le>1.2150000000000000e+02</le></_></splits></_>
    <_>
      <depth>9</depth>
      <value>0.</value>
      <norm_class_idx>0</norm_class_idx>
      <splits>
        <_><var>3</var>
          <quality>2.7586052734375000e+04</quality>
          <le>1.1500000000000000e+01</le></_></splits></_>
    <_>
      <depth>10</depth>
      <value>0.</value>
      <norm_class_idx>0</norm_class_idx></_>
    <_>
      <depth>10</depth>
      <value>0.</value>
      <norm_class_idx>0</norm_class_idx></_>
    <_>
      <depth>9</depth>
      <value>0.</value>
      <norm_class_idx>0</norm_class_idx>
      <splits>
        <_><var>2</var>
          <quality>1.2717854687500000e+05</quality>
          <le>1.5150000000000000e+02</le></_></splits></_>
    <_>
      <depth>10</depth>
      <value>0.</value>
      <norm_class_idx>0</norm_class_idx></_>
    <_>
      <depth>10</depth>
      <value>0.</value>
      <norm_class_idx>0</norm_class_idx></_>
    <_>
      <depth>8</depth>
      <value>0.</value>
      <norm_class_idx>0</norm_class_idx>
      <splits>
        <_><var>0</var>
          <quality>5.7106616210937500e+03</quality>
          <le>1.2350000000000000e+02</le></_></splits></_>
    <_>
      <depth>9</depth>
      <value>0.</value>
      <norm_class_idx>0</norm_class_idx></_>
    <_>
      <depth>9</depth>
      <value>0.</value>
      <norm_class_idx>0</norm_class_idx>
      <splits>
        <_><var>2</var>
          <quality>4.2036025390625000e+03</quality>
          <le>1.5350000000000000e+02</le></_></splits></_>
    <_>
      <depth>10</depth>
      <value>0.</value>
      <norm_class_idx>0</norm_class_idx></_>
    <_>
      <depth>10</depth>
      <value>0.</value>
      <norm_class_idx>0</norm_class_idx></_>
    <_>
      <depth>7</depth>
      <value>0.</value>
      <norm_class_idx>0</norm_class_idx></_>
    <_>
      <depth>3</depth>
      <value>0.</value>
      <norm_class_idx>0</norm_class_idx>
      <splits>
        <_><var>2</var>
          <quality>1.6122473437500000e+05</quality>
          <le>1.4050000000000000e+02</le></_></splits></_>
    <_>
      <depth>4</depth>
      <value>0.</value>
      <norm_class_idx>0</norm_class_idx>
      <splits>
        <_><var>0</var>
          <quality>7.7774406250000000e+04</quality>
          <le>1.6750000000000000e+02</le></_></splits></_>
    <_>
      <depth>5</depth>
      <value>0.</value>
      <norm_class_idx>0</norm_class_idx>
      <splits>
        <_><var>3</var>
          <quality>6.3482523437500000e+04</quality>
          <le>5.5000000000000000e+00</le></_></splits></_>
    <_>
      <depth>6</depth>
      <value>0.</value>
      <norm_class_idx>0</norm_class_idx>
      <splits>
        <_><var>0</var>
          <quality>2.4302886718750000e+04</quality>
          <le>8.6500000000000000e+01</le></_></splits></_>
    <_>
      <depth>7</depth>
      <value>0.</value>
      <norm_class_idx>0</norm_class_idx>
      <splits>
        <_><var>1</var>
          <quality>5.9930556640625000e+03</quality>
          <le>1.4350000000000000e+02</le></_></splits></_>
    <_>
      <depth>8</depth>
      <value>0.</value>
      <norm_class_idx>0</norm_class_idx>
      <splits>
        <_><var>2</var>
          <quality>4.9943496093750000e+03</quality>
          <le>1.3850000000000000e+02</le></_></splits></_>
    <_>
      <depth>9</depth>
      <value>0.</value>
      <norm_class_idx>0</norm_class_idx>
      <splits>
        <_><var>0</var>
          <quality>4.7306796875000000e+03</quality>
          <le>3.6500000000000000e+01</le></_></splits></_>
    <_>
      <depth>10</depth>
      <value>0.</value>
      <norm_class_idx>0</norm_class_idx></_>
    <_>
      <depth>10</depth>
      <value>0.</value>
      <norm_class_idx>0</norm_class_idx></_>
    <_>
      <depth>9</depth>
      <value>0.</value>
      <norm_class_idx>0</norm_class_idx></_>
    <_>
      <depth>8</depth>
      <value>0.</value>
      <norm_class_idx>0</norm_class_idx></_>
    <_>
      <depth>7</depth>
      <value>0.</value>
      <norm_class_idx>0</norm_class_idx>
      <splits>
        <_><var>2</var>
          <quality>1.8356156250000000e+04</quality>
          <le>1.3350000000000000e+02</le></_></splits></_>
    <_>
      <depth>8</depth>
      <value>0.</value>
      <norm_class_idx>0</norm_class_idx>
      <splits>
        <_><var>0</var>
          <quality>2.3902829589843750e+03</quality>
          <le>1.6650000000000000e+02</le></_></splits></_>
    <_>
      <depth>9</depth>
      <value>0.</value>
      <norm_class_idx>0</norm_class_idx>
      <splits>
        <_><var>0</var>
          <quality>2.3548901367187500e+03</quality>
          <le>1.5750000000000000e+02</le></_></splits></_>
    <_>
      <depth>10</depth>
      <value>0.</value>
      <norm_class_idx>0</norm_class_idx></_>
    <_>
      <depth>10</depth>
      <value>0.</value>
      <norm_class_idx>0</norm_class_idx></_>
    <_>
      <depth>9</depth>
      <value>0.</value>
      <norm_class_idx>0</norm_class_idx></_>
    <_>
      <depth>8</depth>
      <value>0.</value>
      <norm_class_idx>0</norm_class_idx>
      <splits>
        <_><var>0</var>
          <quality>1.6015916015625000e+04</quality>
          <le>1.5750000000000000e+02</le></_></splits></_>
    <_>
      <depth>9</depth>
      <value>0.</value>
      <norm_class_idx>0</norm_class_idx>
      <splits>
        <_><var>0</var>
          <quality>1.4060576171875000e+04</quality>
          <le>1.2750000000000000e+02</le></_></splits></_>
    <_>
      <depth>10</depth>
      <value>0.</value>
      <norm_class_idx>0</norm_class_idx></_>
    <_>
      <depth>10</depth>
      <value>0.</value>
      <norm_class_idx>0</norm_class_idx></_>
    <_>
      <depth>9</depth>
      <value>0.</value>
      <norm_class_idx>0</norm_class_idx>
      <splits>
        <_><var>2</var>
          <quality>1.9745566406250000e+03</quality>
          <le>1.3650000000000000e+02</le></_></splits></_>
    <_>
      <depth>10</depth>
      <value>0.</value>
      <norm_class_idx>0</norm_class_idx></_>
    <_>
      <depth>10</depth>
      <value>0.</value>
      <norm_class_idx>0</norm_class_idx></_>
    <_>
      <depth>6</depth>
      <value>0.</value>
      <norm_class_idx>0</norm_class_idx>
      <splits>
        <_><var>3</var>
          <quality>3.9256382812500000e+04</quality>
          <le>1.6050000000000000e+02</le></_></splits></_>
    <_>
      <depth>7</depth>
      <value>0.</value>
      <norm_class_idx>0</norm_class_idx>
      <splits>
        <_><var>0</var>
          <quality>2.0896609375000000e+04</quality>
          <le>1.2450000000000000e+02</le></_></splits></_>
    <_>
      <depth>8</depth>
      <value>0.</value>
      <norm_class_idx>0</norm_class_idx>
      <splits>
        <_><var>3</var>
          <quality>1.1477804687500000e+04</quality>
          <le>7.5000000000000000e+00</le></_></splits></_>
    <_>
      <depth>9</depth>
      <value>0.</value>
      <norm_class_idx>0</norm_class_idx>
      <splits>
        <_><var>0</var>
          <quality>5.7620498046875000e+03</quality>
          <le>6.2500000000000000e+01</le></_></splits></_>
    <_>
      <depth>10</depth>
      <value>0.</value>
      <norm_class_idx>0</norm_class_idx></_>
    <_>
      <depth>10</depth>
      <value>0.</value>
      <norm_class_idx>0</norm_class_idx></_>
    <_>
      <depth>9</depth>
      <value>0.</value>
      <norm_class_idx>0</norm_class_idx>
      <splits>
        <_><var>2</var>
          <quality>5.7342285156250000e+03</quality>
          <le>1.2050000000000000e+02</le></_></splits></_>
    <_>
      <depth>10</depth>
      <value>0.</value>
      <norm_class_idx>0</norm_class_idx></_>
    <_>
      <depth>10</depth>
      <value>0.</value>
      <norm_class_idx>0</norm_class_idx></_>
    <_>
      <depth>8</depth>
      <value>0.</value>
      <norm_class_idx>0</norm_class_idx>
      <splits>
        <_><var>3</var>
          <quality>9.4417978515625000e+03</quality>
          <le>1.4750000000000000e+02</le></_></splits></_>
    <_>
      <depth>9</depth>
      <value>0.</value>
      <norm_class_idx>0</norm_class_idx>
      <splits>
        <_><var>2</var>
          <quality>8.2990048828125000e+03</quality>
          <le>1.1450000000000000e+02</le></_></splits></_>
    <_>
      <depth>10</depth>
      <value>0.</value>
      <norm_class_idx>0</norm_class_idx></_>
    <_>
      <depth>10</depth>
      <value>0.</value>
      <norm_class_idx>0</norm_class_idx></_>
    <_>
      <depth>9</depth>
      <value>0.</value>
      <norm_class_idx>0</norm_class_idx></_>
    <_>
      <depth>7</depth>
      <value>0.</value>
      <norm_class_idx>0</norm_class_idx>
      <splits>
        <_><var>0</var>
          <quality>1.8456285156250000e+04</quality>
          <le>1.4250000000000000e+02</le></_></splits></_>
    <_>
      <depth>8</depth>
      <value>0.</value>
      <norm_class_idx>0</norm_class_idx>
      <splits>
        <_><var>3</var>
          <quality>1.3201143554687500e+04</quality>
          <le>1.7250000000000000e+02</le></_></splits></_>
    <_>
      <depth>9</depth>
      <value>0.</value>
      <norm_class_idx>0</norm_class_idx>
      <splits>
        <_><var>0</var>
          <quality>4.3948183593750000e+03</quality>
          <le>1.3350000000000000e+02</le></_></splits></_>
    <_>
      <depth>10</depth>
      <value>0.</value>
      <norm_class_idx>0</norm_class_idx></_>
    <_>
      <depth>10</depth>
      <value>0.</value>
      <norm_class_idx>0</norm_class_idx></_>
    <_>
      <depth>9</depth>
      <value>0.</value>
      <norm_class_idx>0</norm_class_idx>
      <splits>
        <_><var>0</var>
          <quality>8.8164941406250000e+03</quality>
          <le>6.8500000000000000e+01</le></_></splits></_>
    <_>
      <depth>10</depth>
      <value>0.</value>
      <norm_class_idx>0</norm_class_idx></_>
    <_>
      <depth>10</depth>
      <value>0.</value>
      <norm_class_idx>0</norm_class_idx></_>
    <_>
      <depth>8</depth>
      <value>0.</value>
      <norm_class_idx>0</norm_class_idx>
      <splits>
        <_><var>0</var>
          <quality>5.2839702148437500e+03</quality>
          <le>1.6150000000000000e+02</le></_></splits></_>
    <_>
      <depth>9</depth>
      <value>0.</value>
      <norm_class_idx>0</norm_class_idx>
      <splits>
        <_><var>1</var>
          <quality>4.1682148437500000e+03</quality>
          <le>1.4250000000000000e+02</le></_></splits></_>
    <_>
      <depth>10</depth>
      <value>0.</value>
      <norm_class_idx>0</norm_class_idx></_>
    <_>
      <depth>10</depth>
      <value>0.</value>
      <norm_class_idx>0</norm_class_idx></_>
    <_>
      <depth>9</depth>
      <value>0.</value>
      <norm_class_idx>0</norm_class_idx></_>
    <_>
      <depth>5</depth>
      <value>0.</value>
      <norm_class_idx>0</norm_class_idx>
      <splits>
        <_><var>2</var>
          <quality>1.4409988281250000e+04</quality>
          <le>1.1750000000000000e+02</le></_></splits></_>
    <_>
      <depth>6</depth>
      <value>0.</value>
      <norm_class_idx>0</norm_class_idx></_>
    <_>
      <depth>6</depth>
      <value>0.</value>
      <norm_class_idx>0</norm_class_idx>
      <splits>
        <_><var>0</var>
          <quality>1.4309551757812500e+04</quality>
          <le>1.7350000000000000e+02</le></_></splits></_>
    <_>
      <depth>7</depth>
      <value>0.</value>
      <norm_class_idx>0</norm_class_idx>
      <splits>
        <_><var>2</var>
          <quality>3.1994782714843750e+03</quality>
          <le>1.3450000000000000e+02</le></_></splits></_>
    <_>
      <depth>8</depth>
      <value>0.</value>
      <norm_class_idx>0</norm_class_idx></_>
    <_>
      <depth>8</depth>
      <value>0.</value>
      <norm_class_idx>0</norm_class_idx></_>
    <_>
      <depth>7</depth>
      <value>0.</value>
      <norm_class_idx>0</norm_class_idx>
      <splits>
        <_><var>0</var>
          <quality>1.1114875976562500e+04</quality>
          <le>2.3550000000000000e+02</le></_></splits></_>
    <_>
      <depth>8</depth>
      <value>0.</value>
      <norm_class_idx>0</norm_class_idx>
      <splits>
        <_><var>2</var>
          <quality>1.1089306640625000e+04</quality>
          <le>1.2150000000000000e+02</le></_></splits></_>
    <_>
      <depth>9</depth>
      <value>0.</value>
      <norm_class_idx>0</norm_class_idx></_>
    <_>
      <depth>9</depth>
      <value>0.</value>
      <norm_class_idx>0</norm_class_idx>
      <splits>
        <_><var>1</var>
          <quality>1.0962093750000000e+04</quality>
          <le>1.4350000000000000e+02</le></_></splits></_>
    <_>
      <depth>10</depth>
      <value>0.</value>
      <norm_class_idx>0</norm_class_idx></_>
    <_>
      <depth>10</depth>
      <value>0.</value>
      <norm_class_idx>0</norm_class_idx></_>
    <_>
      <depth>8</depth>
      <value>0.</value>
      <norm_class_idx>0</norm_class_idx></_>
    <_>
      <depth>4</depth>
      <value>0.</value>
      <norm_class_idx>0</norm_class_idx>
      <splits>
        <_><var>3</var>
          <quality>8.3629156250000000e+04</quality>
          <le>7.5000000000000000e+00</le></_></splits></_>
    <_>
      <depth>5</depth>
      <value>0.</value>
      <norm_class_idx>0</norm_class_idx>
      <splits>
        <_><var>0</var>
          <quality>6.4335708007812500e+03</quality>
          <le>1.2250000000000000e+02</le></_></splits></_>
    <_>
      <depth>6</depth>
      <value>0.</value>
      <norm_class_idx>0</norm_class_idx>
      <splits>
        <_><var>2</var>
          <quality>2.8810063476562500e+03</quality>
          <le>1.4150000000000000e+02</le></_></splits></_>
    <_>
      <depth>7</depth>
      <value>0.</value>
      <norm_class_idx>0</norm_class_idx></_>
    <_>
      <depth>7</depth>
      <value>0.</value>
      <norm_class_idx>0</norm_class_idx>
      <splits>
        <_><var>3</var>
          <quality>1.7763066406250000e+03</quality>
          <le>6.5000000000000000e+00</le></_></splits></_>
    <_>
      <depth>8</depth>
      <value>0.</value>
      <norm_class_idx>0</norm_class_idx></_>
    <_>
      <depth>8</depth>
      <value>0.</value>
      <norm_class_idx>0</norm_class_idx></_>
    <_>
      <depth>6</depth>
      <value>0.</value>
      <norm_class_idx>0</norm_class_idx>
      <splits>
        <_><var>0</var>
          <quality>3.5643261718750000e+03</quality>
          <le>1.8750000000000000e+02</le></_></splits></_>
    <_>
      <depth>7</depth>
      <value>0.</value>
      <norm_class_idx>0</norm_class_idx>
      <splits>
        <_><var>0</var>
          <quality>2.9577463378906250e+03</quality>
          <le>1.5150000000000000e+02</le></_></splits></_>
    <_>
      <depth>8</depth>
      <value>0.</value>
      <norm_class_idx>0</norm_class_idx>
      <splits>
        <_><var>1</var>
          <quality>1.8948515625000000e+03</quality>
          <le>1.4450000000000000e+02</le></_></splits></_>
    <_>
      <depth>9</depth>
      <value>0.</value>
      <norm_class_idx>0</norm_class_idx></_>
    <_>
      <depth>9</depth>
      <value>0.</value>
      <norm_class_idx>0</norm_class_idx></_>
    <_>
      <depth>8</depth>
      <value>0.</value>
      <norm_class_idx>0</norm_class_idx></_>
    <_>
      <depth>7</depth>
      <value>0.</value>
      <norm_class_idx>0</norm_class_idx></_>
    <_>
      <depth>5</depth>
      <value>0.</value>
      <norm_class_idx>0</norm_class_idx>
      <splits>
        <_><var>0</var>
          <quality>7.7218531250000000e+04</quality>
          <le>1.1150000000000000e+02</le></_></splits></_>
    <_>
      <depth>6</depth>
      <value>0.</value>
      <norm_class_idx>0</norm_class_idx>
      <splits>
        <_><var>2</var>
          <quality>1.9806785156250000e+04</quality>
          <le>1.6450000000000000e+02</le></_></splits></_>
    <_>
      <depth>7</depth>
      <value>0.</value>
      <norm_class_idx>0</norm_class_idx>
      <splits>
        <_><var>3</var>
          <quality>1.9804882812500000e+04</quality>
          <le>9.5000000000000000e+00</le></_></splits></_>
    <_>
      <depth>8</depth>
      <value>0.</value>
      <norm_class_idx>0</norm_class_idx>
      <splits>
        <_><var>0</var>
          <quality>5.4384384765625000e+03</quality>
          <le>7.3500000000000000e+01</le></_></splits></_>
    <_>
      <depth>9</depth>
      <value>0.</value>
      <norm_class_idx>0</norm_class_idx>
      <splits>
        <_><var>1</var>
          <quality>1.7916802978515625e+03</quality>
          <le>1.4050000000000000e+02</le></_></splits></_>
    <_>
      <depth>10</depth>
      <value>0.</value>
      <norm_class_idx>0</norm_class_idx></_>
    <_>
      <depth>10</depth>
      <value>0.</value>
      <norm_class_idx>0</norm_class_idx></_>
    <_>
      <depth>9</depth>
      <value>0.</value>
      <norm_class_idx>0</norm_class_idx>
      <splits>
        <_><var>2</var>
          <quality>3.6477958984375000e+03</quality>
          <le>1.4250000000000000e+02</le></_></splits></_>
    <_>
      <depth>10</depth>
      <value>0.</value>
      <norm_class_idx>0</norm_class_idx></_>
    <_>
      <depth>10</depth>
      <value>0.</value>
      <norm_class_idx>0</norm_class_idx></_>
    <_>
      <depth>8</depth>
      <value>0.</value>
      <norm_class_idx>0</norm_class_idx>
      <splits>
        <_><var>2</var>
          <quality>1.4369497070312500e+04</quality>
          <le>1.5850000000000000e+02</le></_></splits></_>
    <_>
      <depth>9</depth>
      <value>0.</value>
      <norm_class_idx>0</norm_class_idx>
      <splits>
        <_><var>3</var>
          <quality>1.4283027343750000e+04</quality>
          <le>1.0500000000000000e+01</le></_></splits></_>
    <_>
      <depth>10</depth>
      <value>0.</value>
      <norm_class_idx>0</norm_class_idx></_>
    <_>
      <depth>10</depth>
      <value>0.</value>
      <norm_class_idx>0</norm_class_idx></_>
    <_>
      <depth>9</depth>
      <value>0.</value>
      <norm_class_idx>0</norm_class_idx></_>
    <_>
      <depth>7</depth>
      <value>0.</value>
      <norm_class_idx>0</norm_class_idx></_>
    <_>
      <depth>6</depth>
      <value>0.</value>
      <norm_class_idx>0</norm_class_idx>
      <splits>
        <_><var>0</var>
          <quality>5.7417937500000000e+04</quality>
          <le>1.8250000000000000e+02</le></_></splits></_>
    <_>
      <depth>7</depth>
      <value>0.</value>
      <norm_class_idx>0</norm_class_idx>
      <splits>
        <_><var>3</var>
          <quality>5.0103722656250000e+04</quality>
          <le>9.5000000000000000e+00</le></_></splits></_>
    <_>
      <depth>8</depth>
      <value>0.</value>
      <norm_class_idx>0</norm_class_idx>
      <splits>
        <_><var>0</var>
          <quality>1.0654793945312500e+04</quality>
          <le>1.6950000000000000e+02</le></_></splits></_>
    <_>
      <depth>9</depth>
      <value>0.</value>
      <norm_class_idx>0</norm_class_idx>
      <splits>
        <_><var>3</var>
          <quality>9.6622187500000000e+03</quality>
          <le>8.5000000000000000e+00</le></_></splits></_>
    <_>
      <depth>10</depth>
      <value>0.</value>
      <norm_class_idx>0</norm_class_idx></_>
    <_>
      <depth>10</depth>
      <value>0.</value>
      <norm_class_idx>0</norm_class_idx></_>
    <_>
      <depth>9</depth>
      <value>0.</value>
      <norm_class_idx>0</norm_class_idx></_>
    <_>
      <depth>8</depth>
      <value>0.</value>
      <norm_class_idx>0</norm_class_idx>
      <splits>
        <_><var>2</var>
          <quality>3.9451441406250000e+04</quality>
          <le>1.7450000000000000e+02</le></_></splits></_>
    <_>
      <depth>9</depth>
      <value>0.</value>
      <norm_class_idx>0</norm_class_idx>
      <splits>
        <_><var>3</var>
          <quality>3.9445289062500000e+04</quality>
          <le>1.1500000000000000e+01</le></_></splits></_>
    <_>
      <depth>10</depth>
      <value>0.</value>
      <norm_class_idx>0</norm_class_idx></_>
    <_>
      <depth>10</depth>
      <value>0.</value>
      <norm_class_idx>0</norm_class_idx></_>
    <_>
      <depth>9</depth>
      <value>0.</value>
      <norm_class_idx>0</norm_class_idx></_>
    <_>
      <depth>7</depth>
      <value>0.</value>
      <norm_class_idx>0</norm_class_idx>
      <splits>
        <_><var>0</var>
          <quality>7.3162221679687500e+03</quality>
          <le>1.9050000000000000e+02</le></_></splits></_>
    <_>
      <depth>8</depth>
      <value>0.</value>
      <norm_class_idx>0</norm_class_idx>
      <splits>
        <_><var>2</var>
          <quality>2.0264018554687500e+03</quality>
          <le>1.4550000000000000e+02</le></_></splits></_>
    <_>
      <depth>9</depth>
      <value>0.</value>
      <norm_class_idx>0</norm_class_idx></_>
    <_>
      <depth>9</depth>
      <value>0.</value>
      <norm_class_idx>0</norm_class_idx></_>
    <_>
      <depth>8</depth>
      <value>0.</value>
      <norm_class_idx>0</norm_class_idx>
      <splits>
        <_><var>0</var>
          <quality>5.2900097656250000e+03</quality>
          <le>2.2450000000000000e+02</le></_></splits></_>
    <_>
      <depth>9</depth>
      <value>0.</value>
      <norm_class_idx>0</norm_class_idx>
      <splits>
        <_><var>2</var>
          <quality>5.0400053710937500e+03</quality>
          <le>1.4150000000000000e+02</le></_></splits></_>
    <_>
      <depth>10</depth>
      <value>0.</value>
      <norm_class_idx>0</norm_class_idx></_>
    <_>
      <depth>10</depth>
      <value>0.</value>
      <norm_class_idx>0</norm_class_idx></_>
    <_>
      <depth>9</depth>
      <value>0.</value>
      <norm_class_idx>0</norm_class_idx></_>
    <_>
      <depth>2</depth>
      <value>0.</value>
      <norm_class_idx>0</norm_class_idx>
      <splits>
        <_><var>3</var>
          <quality>8.2098515625000000e+04</quality>
          <le>4.5000000000000000e+00</le></_></splits></_>
    <_>
      <depth>3</depth>
      <value>0.</value>
      <norm_class_idx>0</norm_class_idx>
      <splits>
        <_><var>0</var>
          <quality>1.6717693359375000e+04</quality>
          <le>1.1350000000000000e+02</le></_></splits></_>
    <_>
      <depth>4</depth>
      <value>0.</value>
      <norm_class_idx>0</norm_class_idx>
      <splits>
        <_><var>3</var>
          <quality>6.4878535156250000e+03</quality>
          <le>2.5000000000000000e+00</le></_></splits></_>
    <_>
      <depth>5</depth>
      <value>0.</value>
      <norm_class_idx>0</norm_class_idx>
      <splits>
        <_><var>2</var>
          <quality>3.1758813476562500e+03</quality>
          <le>1.3950000000000000e+02</le></_></splits></_>
    <_>
      <depth>6</depth>
      <value>0.</value>
      <norm_class_idx>0</norm_class_idx>
      <splits>
        <_><var>2</var>
          <quality>1.5951381835937500e+03</quality>
          <le>1.3750000000000000e+02</le></_></splits></_>
    <_>
      <depth>7</depth>
      <value>0.</value>
      <norm_class_idx>0</norm_class_idx></_>
    <_>
      <depth>7</depth>
      <value>0.</value>
      <norm_class_idx>0</norm_class_idx>
      <splits>
        <_><var>2</var>
          <quality>1.0098980102539063e+03</quality>
          <le>1.3850000000000000e+02</le></_></splits></_>
    <_>
      <depth>8</depth>
      <value>0.</value>
      <norm_class_idx>0</norm_class_idx></_>
    <_>
      <depth>8</depth>
      <value>0.</value>
      <norm_class_idx>0</norm_class_idx></_>
    <_>
      <depth>6</depth>
      <value>1.</value>
      <norm_class_idx>1</norm_class_idx>
      <splits>
        <_><var>0</var>
          <quality>1.6279609375000000e+03</quality>
          <le>9.2500000000000000e+01</le></_></splits></_>
    <_>
      <depth>7</depth>
      <value>1.</value>
      <norm_class_idx>1</norm_class_idx></_>
    <_>
      <depth>7</depth>
      <value>0.</value>
      <norm_class_idx>0</norm_class_idx></_>
    <_>
      <depth>5</depth>
      <value>0.</value>
      <norm_class_idx>0</norm_class_idx>
      <splits>
        <_><var>1</var>
          <quality>3.4681911621093750e+03</quality>
          <le>1.5550000000000000e+02</le></_></splits></_>
    <_>
      <depth>6</depth>
      <value>0.</value>
      <norm_class_idx>0</norm_class_idx>
      <splits>
        <_><var>2</var>
          <quality>3.0515058593750000e+03</quality>
          <le>1.4050000000000000e+02</le></_></splits></_>
    <_>
      <depth>7</depth>
      <value>0.</value>
      <norm_class_idx>0</norm_class_idx></_>
    <_>
      <depth>7</depth>
      <value>0.</value>
      <norm_class_idx>0</norm_class_idx>
      <splits>
        <_><var>0</var>
          <quality>2.2647998046875000e+03</quality>
          <le>1.0150000000000000e+02</le></_></splits></_>
    <_>
      <depth>8</depth>
      <value>0.</value>
      <norm_class_idx>0</norm_class_idx>
      <splits>
        <_><var>3</var>
          <quality>1.4858287353515625e+03</quality>
          <le>3.5000000000000000e+00</le></_></splits></_>
    <_>
      <depth>9</depth>
      <value>0.</value>
      <norm_class_idx>0</norm_class_idx></_>
    <_>
      <depth>9</depth>
      <value>0.</value>
      <norm_class_idx>0</norm_class_idx></_>
    <_>
      <depth>8</depth>
      <value>0.</value>
      <norm_class_idx>0</norm_class_idx></_>
    <_>
      <depth>6</depth>
      <value>0.</value>
      <norm_class_idx>0</norm_class_idx></_>
    <_>
      <depth>4</depth>
      <value>0.</value>
      <norm_class_idx>0</norm_class_idx>
      <splits>
        <_><var>1</var>
          <quality>1.0459900390625000e+04</quality>
          <le>1.5550000000000000e+02</le></_></splits></_>
    <_>
      <depth>5</depth>
      <value>0.</value>
      <norm_class_idx>0</norm_class_idx>
      <splits>
        <_><var>0</var>
          <quality>9.8163095703125000e+03</quality>
          <le>1.4650000000000000e+02</le></_></splits></_>
    <_>
      <depth>6</depth>
      <value>0.</value>
      <norm_class_idx>0</norm_class_idx>
      <splits>
        <_><var>2</var>
          <quality>5.9349897460937500e+03</quality>
          <le>1.3750000000000000e+02</le></_></splits></_>
    <_>
      <depth>7</depth>
      <value>0.</value>
      <norm_class_idx>0</norm_class_idx></_>
    <_>
      <depth>7</depth>
      <value>0.</value>
      <norm_class_idx>0</norm_class_idx>
      <splits>
        <_><var>3</var>
          <quality>5.2713305664062500e+03</quality>
          <le>2.5000000000000000e+00</le></_></splits></_>
    <_>
      <depth>8</depth>
      <value>0.</value>
      <norm_class_idx>0</norm_class_idx>
      <splits>
        <_><var>0</var>
          <quality>1.8865839843750000e+03</quality>
          <le>1.3150000000000000e+02</le></_></splits></_>
    <_>
      <depth>9</depth>
      <value>0.</value>
      <norm_class_idx>0</norm_class_idx></_>
    <_>
      <depth>9</depth>
      <value>0.</value>
      <norm_class_idx>0</norm_class_idx></_>
    <_>
      <depth>8</depth>
      <value>0.</value>
      <norm_class_idx>0</norm_class_idx>
      <splits>
        <_><var>0</var>
          <quality>3.4203845214843750e+03</quality>
          <le>1.2650000000000000e+02</le></_></splits></_>
    <_>
      <depth>9</depth>
      <value>0.</value>
      <norm_class_idx>0</norm_class_idx>
      <splits>
        <_><var>2</var>
          <quality>1.4462492675781250e+03</quality>
          <le>1.3850000000000000e+02</le></_></splits></_>
    <_>
      <depth>10</depth>
      <value>1.</value>
      <norm_class_idx>1</norm_class_idx></_>
    <_>
      <depth>10</depth>
      <value>0.</value>
      <norm_class_idx>0</norm_class_idx></_>
    <_>
      <depth>9</depth>
      <value>0.</value>
      <norm_class_idx>0</norm_class_idx>
      <splits>
        <_><var>2</var>
          <quality>1.9973081054687500e+03</quality>
          <le>1.4550000000000000e+02</le></_></splits></_>
    <_>
      <depth>10</depth>
      <value>0.</value>
      <norm_class_idx>0</norm_class_idx></_>
    <_>
      <depth>10</depth>
      <value>0.</value>
      <norm_class_idx>0</norm_class_idx></_>
    <_>
      <depth>6</depth>
      <value>0.</value>
      <norm_class_idx>0</norm_class_idx>
      <splits>
        <_><var>1</var>
          <quality>3.9921230468750000e+03</quality>
          <le>1.5250000000000000e+02</le></_></splits></_>
    <_>
      <depth>7</depth>
      <value>0.</value>
      <norm_class_idx>0</norm_class_idx>
      <splits>
        <_><var>1</var>
          <quality>3.7251342773437500e+03</quality>
          <le>1.4950000000000000e+02</le></_></splits></_>
    <_>
      <depth>8</depth>
      <value>0.</value>
      <norm_class_idx>0</norm_class_idx>
      <splits>
        <_><var>0</var>
          <quality>3.0527897949218750e+03</quality>
          <le>1.6750000000000000e+02</le></_></splits></_>
    <_>
      <depth>9</depth>
      <value>0.</value>
      <norm_class_idx>0</norm_class_idx></_>
    <_>
      <depth>9</depth>
      <value>0.</value>
      <norm_class_idx>0</norm_class_idx></_>
    <_>
      <depth>8</depth>
      <value>0.</value>
      <norm_class_idx>0</norm_class_idx></_>
    <_>
      <depth>7</depth>
      <value>0.</value>
      <norm_class_idx>0</norm_class_idx></_>
    <_>
      <depth>5</depth>
      <value>0.</value>
      <norm_class_idx>0</norm_class_idx></_>
    <_>
      <depth>3</depth>
      <value>0.</value>
      <norm_class_idx>0</norm_class_idx>
      <splits>
        <_><var>3</var>
          <quality>6.6215828125000000e+04</quality>
          <le>1.4350000000000000e+02</le></_></splits></_>
    <_>
      <depth>4</depth>
      <value>0.</value>
      <norm_class_idx>0</norm_class_idx>
      <splits>
        <_><var>3</var>
          <quality>4.6416281250000000e+04</quality>
          <le>6.5000000000000000e+00</le></_></splits></_>
    <_>
      <depth>5</depth>
      <value>0.</value>
      <norm_class_idx>0</norm_class_idx>
      <splits>
        <_><var>0</var>
          <quality>1.2006300781250000e+04</quality>
          <le>1.1450000000000000e+02</le></_></splits></_>
    <_>
      <depth>6</depth>
      <value>0.</value>
      <norm_class_idx>0</norm_class_idx>
      <splits>
        <_><var>1</var>
          <quality>4.8100957031250000e+03</quality>
          <le>1.5350000000000000e+02</le></_></splits></_>
    <_>
      <depth>7</depth>
      <value>0.</value>
      <norm_class_idx>0</norm_class_idx>
      <splits>
        <_><var>0</var>
          <quality>3.3969716796875000e+03</quality>
          <le>1.0150000000000000e+02</le></_></splits></_>
    <_>
      <depth>8</depth>
      <value>0.</value>
      <norm_class_idx>0</norm_class_idx>
      <splits>
        <_><var>2</var>
          <quality>2.2602561035156250e+03</quality>
          <le>1.4750000000000000e+02</le></_></splits></_>
    <_>
      <depth>9</depth>
      <value>0.</value>
      <norm_class_idx>0</norm_class_idx>
      <splits>
        <_><var>0</var>
          <quality>1.6728229980468750e+03</quality>
          <le>5.1500000000000000e+01</le></_></splits></_>
    <_>
      <depth>10</depth>
      <value>0.</value>
      <norm_class_idx>0</norm_class_idx></_>
    <_>
      <depth>10</depth>
      <value>0.</value>
      <norm_class_idx>0</norm_class_idx></_>
    <_>
      <depth>9</depth>
      <value>0.</value>
      <norm_class_idx>0</norm_class_idx></_>
    <_>
      <depth>8</depth>
      <value>0.</value>
      <norm_class_idx>0</norm_class_idx></_>
    <_>
      <depth>7</depth>
      <value>0.</value>
      <norm_class_idx>0</norm_class_idx>
      <splits>
        <_><var>0</var>
          <quality>1.4514205322265625e+03</quality>
          <le>8.0500000000000000e+01</le></_></splits></_>
    <_>
      <depth>8</depth>
      <value>0.</value>
      <norm_class_idx>0</norm_class_idx></_>
    <_>
      <depth>8</depth>
      <value>0.</value>
      <norm_class_idx>0</norm_class_idx></_>
    <_>
      <depth>6</depth>
      <value>0.</value>
      <norm_class_idx>0</norm_class_idx>
      <splits>
        <_><var>0</var>
          <quality>7.2357216796875000e+03</quality>
          <le>1.7750000000000000e+02</le></_></splits></_>
    <_>
      <depth>7</depth>
      <value>0.</value>
      <norm_class_idx>0</norm_class_idx>
      <splits>
        <_><var>1</var>
          <quality>5.5701132812500000e+03</quality>
          <le>1.5450000000000000e+02</le></_></splits></_>
    <_>
      <depth>8</depth>
      <value>0.</value>
      <norm_class_idx>0</norm_class_idx>
      <splits>
        <_><var>1</var>
          <quality>4.9185717773437500e+03</quality>
          <le>1.5050000000000000e+02</le></_></splits></_>
    <_>
      <depth>9</depth>
      <value>0.</value>
      <norm_class_idx>0</norm_class_idx>
      <splits>
        <_><var>0</var>
          <quality>3.5162172851562500e+03</quality>
          <le>1.6450000000000000e+02</le></_></splits></_>
    <_>
      <depth>10</depth>
      <value>0.</value>
      <norm_class_idx>0</norm_class_idx></_>
    <_>
      <depth>10</depth>
      <value>0.</value>
      <norm_class_idx>0</norm_class_idx></_>
    <_>
      <depth>9</depth>
      <value>0.</value>
      <norm_class_idx>0</norm_class_idx></_>
    <_>
      <depth>8</depth>
      <value>0.</value>
      <norm_class_idx>0</norm_class_idx></_>
    <_>
      <depth>7</depth>
      <value>0.</value>
      <norm_class_idx>0</norm_class_idx></_>
    <_>
      <depth>5</depth>
      <value>0.</value>
      <norm_class_idx>0</norm_class_idx>
      <splits>
        <_><var>0</var>
          <quality>3.4494949218750000e+04</quality>
          <le>1.4450000000000000e+02</le></_></splits></_>
    <_>
      <depth>6</depth>
      <value>0.</value>
      <norm_class_idx>0</norm_class_idx>
      <splits>
        <_><var>3</var>
          <quality>1.9730396484375000e+04</quality>
          <le>7.5000000000000000e+00</le></_></splits></_>
    <_>
      <depth>7</depth>
      <value>0.</value>
      <norm_class_idx>0</norm_class_idx>
      <splits>
        <_><var>1</var>
          <quality>4.5463417968750000e+03</quality>
          <le>1.4850000000000000e+02</le></_></splits></_>
    <_>
      <depth>8</depth>
      <value>0.</value>
      <norm_class_idx>0</norm_class_idx>
      <splits>
        <_><var>0</var>
          <quality>1.7279324951171875e+03</quality>
          <le>1.3050000000000000e+02</le></_></splits></_>
    <_>
      <depth>9</depth>
      <value>0.</value>
      <norm_class_idx>0</norm_class_idx></_>
    <_>
      <depth>9</depth>
      <value>0.</value>
      <norm_class_idx>0</norm_class_idx></_>
    <_>
      <depth>8</depth>
      <value>0.</value>
      <norm_class_idx>0</norm_class_idx>
      <splits>
        <_><var>2</var>
          <quality>2.8218884277343750e+03</quality>
          <le>1.5550000000000000e+02</le></_></splits></_>
    <_>
      <depth>9</depth>
      <value>0.</value>
      <norm_class_idx>0</norm_class_idx>
      <splits>
        <_><var>0</var>
          <quality>2.3145815429687500e+03</quality>
          <le>1.0850000000000000e+02</le></_></splits></_>
    <_>
      <depth>10</depth>
      <value>0.</value>
      <norm_class_idx>0</norm_class_idx></_>
    <_>
      <depth>10</depth>
      <value>0.</value>
      <norm_class_idx>0</norm_class_idx></_>
    <_>
      <depth>9</depth>
      <value>0.</value>
      <norm_class_idx>0</norm_class_idx></_>
    <_>
      <depth>7</depth>
      <value>0.</value>
      <norm_class_idx>0</norm_class_idx>
      <splits>
        <_><var>0</var>
          <quality>1.5194242187500000e+04</quality>
          <le>9.8500000000000000e+01</le></_></splits></_>
    <_>
      <depth>8</depth>
      <value>0.</value>
      <norm_class_idx>0</norm_class_idx>
      <splits>
        <_><var>2</var>
          <quality>3.1094475097656250e+03</quality>
          <le>1.6150000000000000e+02</le></_></splits></_>
    <_>
      <depth>9</depth>
      <value>0.</value>
      <norm_class_idx>0</norm_class_idx>
      <splits>
        <_><var>2</var>
          <quality>3.0753029785156250e+03</quality>
          <le>1.5950000000000000e+02</le></_></splits></_>
    <_>
      <depth>10</depth>
      <value>0.</value>
      <norm_class_idx>0</norm_class_idx></_>
    <_>
      <depth>10</depth>
      <value>0.</value>
      <norm_class_idx>0</norm_class_idx></_>
    <_>
      <depth>9</depth>
      <value>0.</value>
      <norm_class_idx>0</norm_class_idx></_>
    <_>
      <depth>8</depth>
      <value>0.</value>
      <norm_class_idx>0</norm_class_idx>
      <splits>
        <_><var>3</var>
          <quality>1.2110850585937500e+04</quality>
          <le>9.5000000000000000e+00</le></_></splits></_>
    <_>
      <depth>9</depth>
      <value>0.</value>
      <norm_class_idx>0</norm_class_idx>
      <splits>
        <_><var>1</var>
          <quality>6.3848090820312500e+03</quality>
          <le>1.4850000000000000e+02</le></_></splits></_>
    <_>
      <depth>10</depth>
      <value>0.</value>
      <norm_class_idx>0</norm_class_idx></_>
    <_>
      <depth>10</depth>
      <value>0.</value>
      <norm_class_idx>0</norm_class_idx></_>
    <_>
      <depth>9</depth>
      <value>0.</value>
      <norm_class_idx>0</norm_class_idx>
      <splits>
        <_><var>2</var>
          <quality>5.7288076171875000e+03</quality>
          <le>1.6250000000000000e+02</le></_></splits></_>
    <_>
      <depth>10</depth>
      <value>0.</value>
      <norm_class_idx>0</norm_class_idx></_>
    <_>
      <depth>10</depth>
      <value>0.</value>
      <norm_class_idx>0</norm_class_idx></_>
    <_>
      <depth>6</depth>
      <value>0.</value>
      <norm_class_idx>0</norm_class_idx>
      <splits>
        <_><var>0</var>
          <quality>1.4776241210937500e+04</quality>
          <le>1.6550000000000000e+02</le></_></splits></_>
    <_>
      <depth>7</depth>
      <value>0.</value>
      <norm_class_idx>0</norm_class_idx>
      <splits>
        <_><var>3</var>
          <quality>6.1947363281250000e+03</quality>
          <le>7.5000000000000000e+00</le></_></splits></_>
    <_>
      <depth>8</depth>
      <value>0.</value>
      <norm_class_idx>0</norm_class_idx></_>
    <_>
      <depth>8</depth>
      <value>0.</value>
      <norm_class_idx>0</norm_class_idx>
      <splits>
        <_><var>2</var>
          <quality>5.1027983398437500e+03</quality>
          <le>1.5850000000000000e+02</le></_></splits></_>
    <_>
      <depth>9</depth>
      <value>0.</value>
      <norm_class_idx>0</norm_class_idx>
      <splits>
        <_><var>0</var>
          <quality>3336.</quality>
          <le>1.5950000000000000e+02</le></_></splits></_>
    <_>
      <depth>10</depth>
      <value>0.</value>
      <norm_class_idx>0</norm_class_idx></_>
    <_>
      <depth>10</depth>
      <value>0.</value>
      <norm_class_idx>0</norm_class_idx></_>
    <_>
      <depth>9</depth>
      <value>0.</value>
      <norm_class_idx>0</norm_class_idx>
      <splits>
        <_><var>2</var>
          <quality>1.7674405517578125e+03</quality>
          <le>1.7550000000000000e+02</le></_></splits></_>
    <_>
      <depth>10</depth>
      <value>0.</value>
      <norm_class_idx>0</norm_class_idx></_>
    <_>
      <depth>10</depth>
      <value>0.</value>
      <norm_class_idx>0</norm_class_idx></_>
    <_>
      <depth>7</depth>
      <value>0.</value>
      <norm_class_idx>0</norm_class_idx>
      <splits>
        <_><var>3</var>
          <quality>8.5834433593750000e+03</quality>
          <le>7.5000000000000000e+00</le></_></splits></_>
    <_>
      <depth>8</depth>
      <value>0.</value>
      <norm_class_idx>0</norm_class_idx></_>
    <_>
      <depth>8</depth>
      <value>0.</value>
      <norm_class_idx>0</norm_class_idx>
      <splits>
        <_><var>2</var>
          <quality>7.2453466796875000e+03</quality>
          <le>1.4550000000000000e+02</le></_></splits></_>
    <_>
      <depth>9</depth>
      <value>0.</value>
      <norm_class_idx>0</norm_class_idx></_>
    <_>
      <depth>9</depth>
      <value>0.</value>
      <norm_class_idx>0</norm_class_idx>
      <splits>
        <_><var>2</var>
          <quality>7.2250537109375000e+03</quality>
          <le>1.4650000000000000e+02</le></_></splits></_>
    <_>
      <depth>10</depth>
      <value>0.</value>
      <norm_class_idx>0</norm_class_idx></_>
    <_>
      <depth>10</depth>
      <value>0.</value>
      <norm_class_idx>0</norm_class_idx></_>
    <_>
      <depth>4</depth>
      <value>0.</value>
      <norm_class_idx>0</norm_class_idx>
      <splits>
        <_><var>2</var>
          <quality>2.0415427734375000e+04</quality>
          <le>1.3750000000000000e+02</le></_></splits></_>
    <_>
      <depth>5</depth>
      <value>0.</value>
      <norm_class_idx>0</norm_class_idx>
      <splits>
        <_><var>1</var>
          <quality>1.9572859375000000e+04</quality>
          <le>1.5150000000000000e+02</le></_></splits></_>
    <_>
      <depth>6</depth>
      <value>0.</value>
      <norm_class_idx>0</norm_class_idx>
      <splits>
        <_><var>2</var>
          <quality>1.2868564453125000e+04</quality>
          <le>1.3550000000000000e+02</le></_></splits></_>
    <_>
      <depth>7</depth>
      <value>0.</value>
      <norm_class_idx>0</norm_class_idx>
      <splits>
        <_><var>0</var>
          <quality>1.1997219726562500e+04</quality>
          <le>1.5350000000000000e+02</le></_></splits></_>
    <_>
      <depth>8</depth>
      <value>0.</value>
      <norm_class_idx>0</norm_class_idx>
      <splits>
        <_><var>0</var>
          <quality>8.8459296875000000e+03</quality>
          <le>7.9500000000000000e+01</le></_></splits></_>
    <_>
      <depth>9</depth>
      <value>0.</value>
      <norm_class_idx>0</norm_class_idx></_>
    <_>
      <depth>9</depth>
      <value>0.</value>
      <norm_class_idx>0</norm_class_idx>
      <splits>
        <_><var>1</var>
          <quality>7.6499956054687500e+03</quality>
          <le>1.5050000000000000e+02</le></_></splits></_>
    <_>
      <depth>10</depth>
      <value>0.</value>
      <norm_class_idx>0</norm_class_idx></_>
    <_>
      <depth>10</depth>
      <value>0.</value>
      <norm_class_idx>0</norm_class_idx></_>
    <_>
      <depth>8</depth>
      <value>0.</value>
      <norm_class_idx>0</norm_class_idx>
      <splits>
        <_><var>3</var>
          <quality>3.1753728027343750e+03</quality>
          <le>1.5950000000000000e+02</le></_></splits></_>
    <_>
      <depth>9</depth>
      <value>0.</value>
      <norm_class_idx>0</norm_class_idx></_>
    <_>
      <depth>9</depth>
      <value>0.</value>
      <norm_class_idx>0</norm_class_idx>
      <splits>
        <_><var>1</var>
          <quality>3.1256791992187500e+03</quality>
          <le>1.4750000000000000e+02</le></_></splits></_>
    <_>
      <depth>10</depth>
      <value>0.</value>
      <norm_class_idx>0</norm_class_idx></_>
    <_>
      <depth>10</depth>
      <value>0.</value>
      <norm_class_idx>0</norm_class_idx></_>
    <_>
      <depth>7</depth>
      <value>0.</value>
      <norm_class_idx>0</norm_class_idx></_>
    <_>
      <depth>6</depth>
      <value>0.</value>
      <norm_class_idx>0</norm_class_idx>
      <splits>
        <_><var>0</var>
          <quality>6.8312065429687500e+03</quality>
          <le>1.3950000000000000e+02</le></_></splits></_>
    <_>
      <depth>7</depth>
      <value>0.</value>
      <norm_class_idx>0</norm_class_idx>
      <splits>
        <_><var>3</var>
          <quality>4.0765366210937500e+03</quality>
          <le>1.7450000000000000e+02</le></_></splits></_>
    <_>
      <depth>8</depth>
      <value>0.</value>
      <norm_class_idx>0</norm_class_idx>
      <splits>
        <_><var>0</var>
          <quality>2.5899721679687500e+03</quality>
          <le>5.5500000000000000e+01</le></_></splits></_>
    <_>
      <depth>9</depth>
      <value>0.</value>
      <norm_class_idx>0</norm_class_idx></_>
    <_>
      <depth>9</depth>
      <value>0.</value>
      <norm_class_idx>0</norm_class_idx>
      <splits>
        <_><var>2</var>
          <quality>2.1267995605468750e+03</quality>
          <le>1.2050000000000000e+02</le></_></splits></_>
    <_>
      <depth>10</depth>
      <value>0.</value>
      <norm_class_idx>0</norm_class_idx></_>
    <_>
      <depth>10</depth>
      <value>0.</value>
      <norm_class_idx>0</norm_class_idx></_>
    <_>
      <depth>8</depth>
      <value>0.</value>
      <norm_class_idx>0</norm_class_idx>
      <splits>
        <_><var>0</var>
          <quality>1.5270041503906250e+03</quality>
          <le>8.9500000000000000e+01</le></_></splits></_>
    <_>
      <depth>9</depth>
      <value>0.</value>
      <norm_class_idx>0</norm_class_idx></_>
    <_>
      <depth>9</depth>
      <value>0.</value>
      <norm_class_idx>0</norm_class_idx>
      <splits>
        <_><var>1</var>
          <quality>1.2037875976562500e+03</quality>
          <le>1.5650000000000000e+02</le></_></splits></_>
    <_>
      <depth>10</depth>
      <value>0.</value>
      <norm_class_idx>0</norm_class_idx></_>
    <_>
      <depth>10</depth>
      <value>0.</value>
      <norm_class_idx>0</norm_class_idx></_>
    <_>
      <depth>7</depth>
      <value>0.</value>
      <norm_class_idx>0</norm_class_idx>
      <splits>
        <_><var>0</var>
          <quality>2.8011345214843750e+03</quality>
          <le>1.6750000000000000e+02</le></_></splits></_>
    <_>
      <depth>8</depth>
      <value>0.</value>
      <norm_class_idx>0</norm_class_idx>
      <splits>
        <_><var>3</var>
          <quality>1.6864215087890625e+03</quality>
          <le>1.5650000000000000e+02</le></_></splits></_>
    <_>
      <depth>9</depth>
      <value>1.</value>
      <norm_class_idx>1</norm_class_idx></_>
    <_>
      <depth>9</depth>
      <value>0.</value>
      <norm_class_idx>0</norm_class_idx>
      <splits>
        <_><var>0</var>
          <quality>1.6833045654296875e+03</quality>
          <le>1.4650000000000000e+02</le></_></splits></_>
    <_>
      <depth>10</depth>
      <value>0.</value>
      <norm_class_idx>0</norm_class_idx></_>
    <_>
      <depth>10</depth>
      <value>0.</value>
      <norm_class_idx>0</norm_class_idx></_>
    <_>
      <depth>8</depth>
      <value>0.</value>
      <norm_class_idx>0</norm_class_idx></_>
    <_>
      <depth>5</depth>
      <value>0.</value>
      <norm_class_idx>0</norm_class_idx>
      <splits>
        <_><var>2</var>
          <quality>1.0033900756835938e+03</quality>
          <le>1.3950000000000000e+02</le></_></splits></_>
    <_>
      <depth>6</depth>
      <value>0.</value>
      <norm_class_idx>0</norm_class_idx></_>
    <_>
      <depth>6</depth>
      <value>1.</value>
      <norm_class_idx>1</norm_class_idx></_>
    <_>
      <depth>1</depth>
      <value>0.</value>
      <norm_class_idx>0</norm_class_idx>
      <splits>
        <_><var>2</var>
          <quality>1.5478150390625000e+04</quality>
          <le>1.3650000000000000e+02</le></_></splits></_>
    <_>
      <depth>2</depth>
      <value>0.</value>
      <norm_class_idx>0</norm_class_idx>
      <splits>
        <_><var>2</var>
          <quality>4.6670087890625000e+03</quality>
          <le>1.2650000000000000e+02</le></_></splits></_>
    <_>
      <depth>3</depth>
      <value>0.</value>
      <norm_class_idx>0</norm_class_idx>
      <splits>
        <_><var>2</var>
          <quality>2.5255148925781250e+03</quality>
          <le>5.6500000000000000e+01</le></_></splits></_>
    <_>
      <depth>4</depth>
      <value>1.</value>
      <norm_class_idx>1</norm_class_idx></_>
    <_>
      <depth>4</depth>
      <value>0.</value>
      <norm_class_idx>0</norm_class_idx>
      <splits>
        <_><var>1</var>
          <quality>2.5161572265625000e+03</quality>
          <le>1.6350000000000000e+02</le></_></splits></_>
    <_>
      <depth>5</depth>
      <value>0.</value>
      <norm_class_idx>0</norm_class_idx></_>
    <_>
      <depth>5</depth>
      <value>0.</value>
      <norm_class_idx>0</norm_class_idx>
      <splits>
        <_><var>2</var>
          <quality>1.8659555664062500e+03</quality>
          <le>1.2550000000000000e+02</le></_></splits></_>
    <_>
      <depth>6</depth>
      <value>0.</value>
      <norm_class_idx>0</norm_class_idx>
      <splits>
        <_><var>1</var>
          <quality>1.7505292968750000e+03</quality>
          <le>1.6650000000000000e+02</le></_></splits></_>
    <_>
      <depth>7</depth>
      <value>0.</value>
      <norm_class_idx>0</norm_class_idx></_>
    <_>
      <depth>7</depth>
      <value>0.</value>
      <norm_class_idx>0</norm_class_idx></_>
    <_>
      <depth>6</depth>
      <value>0.</value>
      <norm_class_idx>0</norm_class_idx></_>
    <_>
      <depth>3</depth>
      <value>0.</value>
      <norm_class_idx>0</norm_class_idx>
      <splits>
        <_><var>0</var>
          <quality>2.2493344726562500e+03</quality>
          <le>7.4500000000000000e+01</le></_></splits></_>
    <_>
      <depth>4</depth>
      <value>0.</value>
      <norm_class_idx>0</norm_class_idx></_>
    <_>
      <depth>4</depth>
      <value>0.</value>
      <norm_class_idx>0</norm_class_idx>
      <splits>
        <_><var>0</var>
          <quality>1.5381473388671875e+03</quality>
          <le>1.4150000000000000e+02</le></_></splits></_>
    <_>
      <depth>5</depth>
      <value>0.</value>
      <norm_class_idx>0</norm_class_idx>
      <splits>
        <_><var>1</var>
          <quality>1.1616943359375000e+03</quality>
          <le>1.7350000000000000e+02</le></_></splits></_>
    <_>
      <depth>6</depth>
      <value>0.</value>
      <norm_class_idx>0</norm_class_idx>
      <splits>
        <_><var>0</var>
          <quality>1.0408260498046875e+03</quality>
          <le>1.2250000000000000e+02</le></_></splits></_>
    <_>
      <depth>7</depth>
      <value>0.</value>
      <norm_class_idx>0</norm_class_idx></_>
    <_>
      <depth>7</depth>
      <value>0.</value>
      <norm_class_idx>0</norm_class_idx></_>
    <_>
      <depth>6</depth>
      <value>0.</value>
      <norm_class_idx>0</norm_class_idx></_>
    <_>
      <depth>5</depth>
      <value>0.</value>
      <norm_class_idx>0</norm_class_idx></_>
    <_>
      <depth>2</depth>
      <value>1.</value>
      <norm_class_idx>1</norm_class_idx>
      <splits>
        <_><var>1</var>
          <quality>1.1773199218750000e+04</quality>
          <le>1.6550000000000000e+02</le></_></splits></_>
    <_>
      <depth>3</depth>
      <value>0.</value>
      <norm_class_idx>0</norm_class_idx>
      <splits>
        <_><var>2</var>
          <quality>5.8918393554687500e+03</quality>
          <le>1.5350000000000000e+02</le></_></splits></_>
    <_>
      <depth>4</depth>
      <value>1.</value>
      <norm_class_idx>1</norm_class_idx>
      <splits>
        <_><var>0</var>
          <quality>3.2546923828125000e+03</quality>
          <le>1.3950000000000000e+02</le></_></splits></_>
    <_>
      <depth>5</depth>
      <value>1.</value>
      <norm_class_idx>1</norm_class_idx>
      <splits>
        <_><var>1</var>
          <quality>2.7739711914062500e+03</quality>
          <le>1.6150000000000000e+02</le></_></splits></_>
    <_>
      <depth>6</depth>
      <value>1.</value>
      <norm_class_idx>1</norm_class_idx>
      <splits>
        <_><var>2</var>
          <quality>9.4419610595703125e+02</quality>
          <le>1.3850000000000000e+02</le></_></splits></_>
    <_>
      <depth>7</depth>
      <value>0.</value>
      <norm_class_idx>0</norm_class_idx></_>
    <_>
      <depth>7</depth>
      <value>1.</value>
      <norm_class_idx>1</norm_class_idx></_>
    <_>
      <depth>6</depth>
      <value>1.</value>
      <norm_class_idx>1</norm_class_idx>
      <splits>
        <_><var>3</var>
          <quality>1.8710172119140625e+03</quality>
          <le>1.7650000000000000e+02</le></_></splits></_>
    <_>
      <depth>7</depth>
      <value>1.</value>
      <norm_class_idx>1</norm_class_idx>
      <splits>
        <_><var>0</var>
          <quality>1.1523709716796875e+03</quality>
          <le>6.4500000000000000e+01</le></_></splits></_>
    <_>
      <depth>8</depth>
      <value>0.</value>
      <norm_class_idx>0</norm_class_idx></_>
    <_>
      <depth>8</depth>
      <value>1.</value>
      <norm_class_idx>1</norm_class_idx>
      <splits>
        <_><var>0</var>
          <quality>1.0613890380859375e+03</quality>
          <le>1.0750000000000000e+02</le></_></splits></_>
    <_>
      <depth>9</depth>
      <value>1.</value>
      <norm_class_idx>1</norm_class_idx></_>
    <_>
      <depth>9</depth>
      <value>1.</value>
      <norm_class_idx>1</norm_class_idx></_>
    <_>
      <depth>7</depth>
      <value>1.</value>
      <norm_class_idx>1</norm_class_idx></_>
    <_>
      <depth>5</depth>
      <value>0.</value>
      <norm_class_idx>0</norm_class_idx></_>
    <_>
      <depth>4</depth>
      <value>0.</value>
      <norm_class_idx>0</norm_class_idx>
      <splits>
        <_><var>2</var>
          <quality>2.7676899414062500e+03</quality>
          <le>1.5650000000000000e+02</le></_></splits></_>
    <_>
      <depth>5</depth>
      <value>0.</value>
      <norm_class_idx>0</norm_class_idx></_>
    <_>
      <depth>5</depth>
      <value>0.</value>
      <norm_class_idx>0</norm_class_idx>
      <splits>
        <_><var>3</var>
          <quality>2.1718017578125000e+03</quality>
          <le>6.5000000000000000e+00</le></_></splits></_>
    <_>
      <depth>6</depth>
      <value>0.</value>
      <norm_class_idx>0</norm_class_idx></_>
    <_>
      <depth>6</depth>
      <value>0.</value>
      <norm_class_idx>0</norm_class_idx></_>
    <_>
      <depth>3</depth>
      <value>1.</value>
      <norm_class_idx>1</norm_class_idx>
      <splits>
        <_><var>0</var>
          <quality>7.0445332031250000e+03</quality>
          <le>1.5150000000000000e+02</le></_></splits></_>
    <_>
      <depth>4</depth>
      <value>1.</value>
      <norm_class_idx>1</norm_class_idx>
      <splits>
        <_><var>3</var>
          <quality>6.8008916015625000e+03</quality>
          <le>2.5000000000000000e+00</le></_></splits></_>
    <_>
      <depth>5</depth>
      <value>1.</value>
      <norm_class_idx>1</norm_class_idx>
      <splits>
        <_><var>1</var>
          <quality>2.1226870117187500e+03</quality>
          <le>1.6950000000000000e+02</le></_></splits></_>
    <_>
      <depth>6</depth>
      <value>1.</value>
      <norm_class_idx>1</norm_class_idx></_>
    <_>
      <depth>6</depth>
      <value>1.</value>
      <norm_class_idx>1</norm_class_idx>
      <splits>
        <_><var>1</var>
          <quality>1.4945095214843750e+03</quality>
          <le>1.8050000000000000e+02</le></_></splits></_>
    <_>
      <depth>7</depth>
      <value>1.</value>
      <norm_class_idx>1</norm_class_idx></_>
    <_>
      <depth>7</depth>
      <value>1.</value>
      <norm_class_idx>1</norm_class_idx></_>
    <_>
      <depth>5</depth>
      <value>1.</value>
      <norm_class_idx>1</norm_class_idx>
      <splits>
        <_><var>3</var>
          <quality>5.0195537109375000e+03</quality>
          <le>1.7550000000000000e+02</le></_></splits></_>
    <_>
      <depth>6</depth>
      <value>0.</value>
      <norm_class_idx>0</norm_class_idx>
      <splits>
        <_><var>3</var>
          <quality>1.5552089843750000e+03</quality>
          <le>4.5000000000000000e+00</le></_></splits></_>
    <_>
      <depth>7</depth>
      <value>1.</value>
      <norm_class_idx>1</norm_class_idx></_>
    <_>
      <depth>7</depth>
      <value>0.</value>
      <norm_class_idx>0</norm_class_idx>
      <splits>
        <_><var>2</var>
          <quality>1.0890970458984375e+03</quality>
          <le>1.4250000000000000e+02</le></_></splits></_>
    <_>
      <depth>8</depth>
      <value>1.</value>
      <norm_class_idx>1</norm_class_idx></_>
    <_>
      <depth>8</depth>
      <value>0.</value>
      <norm_class_idx>0</norm_class_idx></_>
    <_>
      <depth>6</depth>
      <value>1.</value>
      <norm_class_idx>1</norm_class_idx>
      <splits>
        <_><var>0</var>
          <quality>3.6379042968750000e+03</quality>
          <le>1.0550000000000000e+02</le></_></splits></_>
    <_>
      <depth>7</depth>
      <value>1.</value>
      <norm_class_idx>1</norm_class_idx>
      <splits>
        <_><var>3</var>
          <quality>2.4726193847656250e+03</quality>
          <le>1.7750000000000000e+02</le></_></splits></_>
    <_>
      <depth>8</depth>
      <value>1.</value>
      <norm_class_idx>1</norm_class_idx></_>
    <_>
      <depth>8</depth>
      <value>1.</value>
      <norm_class_idx>1</norm_class_idx></_>
    <_>
      <depth>7</depth>
      <value>1.</value>
      <norm_class_idx>1</norm_class_idx>
      <splits>
        <_><var>2</var>
          <quality>1.2053421630859375e+03</quality>
          <le>1.5650000000000000e+02</le></_></splits></_>
    <_>
      <depth>8</depth>
      <value>1.</value>
      <norm_class_idx>1</norm_class_idx>
      <splits>
        <_><var>1</var>
          <quality>1.0920880126953125e+03</quality>
          <le>1.7850000000000000e+02</le></_></splits></_>
    <_>
      <depth>9</depth>
      <value>1.</value>
      <norm_class_idx>1</norm_class_idx></_>
    <_>
      <depth>9</depth>
      <value>0.</value>
      <norm_class_idx>0</norm_class_idx></_>
    <_>
      <depth>8</depth>
      <value>1.</value>
      <norm_class_idx>1</norm_class_idx></_>
    <_>
      <depth>4</depth>
      <value>0.</value>
      <norm_class_idx>0</norm_class_idx></_></nodes></opencv_ml_dtree>
</opencv_storage>
